gambling/__init__.py
gambling/cards.py
gambling/dice.py
gambling/player.py
gambling-1.0.0.dev2.dist-info/LICENSE.txt
gambling-1.0.0.dev2.dist-info/METADATA
gambling-1.0.0.dev2.dist-info/WHEEL
gambling-1.0.0.dev2.dist-info/top_level.txt
gambling-1.0.0.dev2.dist-info/RECORD
