Metadata-Version: 2.1
Name: gambling
Version: 1.0.0.dev2
Summary: A gambling package for Cards, Dice, and Blackjack
Home-page: https://github.com/SubZeb/gambling
Author: CJ Stein
Author-email: resume@cjstein.com
License: UNKNOWN
Project-URL: Bug Tracker, https://github.com/SubZeb/gambling/issues
Platform: UNKNOWN
Classifier: Programming Language :: Python :: 3
Classifier: License :: OSI Approved :: MIT License
Classifier: Operating System :: OS Independent
Requires-Python: >=3.6
License-File: LICENSE.txt
